Metadata-Version: 2.1
Name: xploreds
Version: 0.0.1
Summary: Easy-to-use package of the most relevant Data Science techniques.
Home-page: https://github.com/danieldominguete/XploreDS
Author: Daniel Dominguete
Author-email: daniel.dominguete@gmail.com
License: MIT License
Keywords: Data Science
License-File: LICENSE
